jupyterlab_theme_sophon/__init__.py
jupyterlab_theme_sophon/_version.py
jupyterlab_theme_sophon/labextension/package.json
jupyterlab_theme_sophon/labextension/static/568.23f7ef1d2884a3764ad5.js
jupyterlab_theme_sophon/labextension/static/remoteEntry.7cdd4718761d6408b8ba.js
jupyterlab_theme_sophon/labextension/static/style.js
jupyterlab_theme_sophon/labextension/static/third-party-licenses.json
jupyterlab_theme_sophon/labextension/themes/jupyterlab_theme_sophon/index.css
jupyterlab_theme_sophon/labextension/themes/jupyterlab_theme_sophon/index.js
jupyterlab_theme_sophon-0.1.0.data/data/share/jupyter/labextensions/jupyterlab_theme_sophon/install.json
jupyterlab_theme_sophon-0.1.0.data/data/share/jupyter/labextensions/jupyterlab_theme_sophon/package.json
jupyterlab_theme_sophon-0.1.0.data/data/share/jupyter/labextensions/jupyterlab_theme_sophon/static/568.23f7ef1d2884a3764ad5.js
jupyterlab_theme_sophon-0.1.0.data/data/share/jupyter/labextensions/jupyterlab_theme_sophon/static/remoteEntry.7cdd4718761d6408b8ba.js
jupyterlab_theme_sophon-0.1.0.data/data/share/jupyter/labextensions/jupyterlab_theme_sophon/static/style.js
jupyterlab_theme_sophon-0.1.0.data/data/share/jupyter/labextensions/jupyterlab_theme_sophon/static/third-party-licenses.json
jupyterlab_theme_sophon-0.1.0.data/data/share/jupyter/labextensions/jupyterlab_theme_sophon/themes/jupyterlab_theme_sophon/index.css
jupyterlab_theme_sophon-0.1.0.data/data/share/jupyter/labextensions/jupyterlab_theme_sophon/themes/jupyterlab_theme_sophon/index.js
jupyterlab_theme_sophon-0.1.0.dist-info/LICENSE
jupyterlab_theme_sophon-0.1.0.dist-info/METADATA
jupyterlab_theme_sophon-0.1.0.dist-info/WHEEL
jupyterlab_theme_sophon-0.1.0.dist-info/top_level.txt
jupyterlab_theme_sophon-0.1.0.dist-info/RECORD
